geojson_to_sqlite/__init__.py
geojson_to_sqlite/cli.py
geojson_to_sqlite/utils.py
geojson_to_sqlite-1.1.1.dist-info/LICENSE
geojson_to_sqlite-1.1.1.dist-info/METADATA
geojson_to_sqlite-1.1.1.dist-info/WHEEL
geojson_to_sqlite-1.1.1.dist-info/entry_points.txt
geojson_to_sqlite-1.1.1.dist-info/top_level.txt
geojson_to_sqlite-1.1.1.dist-info/RECORD
