Metadata-Version: 2.1
Name: geojson-to-sqlite
Version: 1.1.1
Summary: CLI tool for converting GeoJSON to SQLite (optionally with SpatiaLite)
Home-page: https://github.com/simonw/geojson-to-sqlite
Author: Simon Willison
License: Apache License, Version 2.0
Platform: UNKNOWN
License-File: LICENSE
Requires-Dist: sqlite-utils (>=3.23)
Requires-Dist: shapely
Provides-Extra: test
Requires-Dist: pytest ; extra == 'test'
Requires-Dist: dirty-equals ; extra == 'test'
